{"name":"考研C语言","slug":"考研C语言","count":1,"postlist":[{"title":"C语言符号的优先级","uid":"0835c4181310b6f3180f9660dba8facf","slug":"C语言符号的优先级","date":"2023-10-27T13:55:46.000Z","updated":"2023-10-27T14:51:57.222Z","comments":true,"path":"api/articles/C语言符号的优先级.json","keywords":null,"cover":null,"text":"前言在不管是考研还是计算机二级等考试中，总会遇到一些关于C语言运算符优先级的问题。但是记忆还是比较困难的一件事情。 分类在C语言中运算符主要有以下几类：算术运算符、逻辑运算符、关系运算符、位运算符、 赋值运算符、 递增和递减运算符、条件运算符。 算术运算符 算术运算符主要是指像 ...","link":"","photos":[],"count_time":{"symbolsCount":"1k","symbolsTime":"1 mins."},"categories":[],"tags":[{"name":"考研C语言","slug":"考研C语言","count":1,"path":"api/tags/考研C语言.json"}],"author":{"name":"Gaoth","slug":"gaoth","avatar":"https://s2.loli.net/2022/10/24/zZ5Msr7bhigQVcj.jpg","link":"/","description":"不以为然的存在，细品起来会得到意想不到的有趣。<br /> @<b>公众号：噜啦啦小栈</b>","socials":{"github":"https://github.com//githubforgth","twitter":"","stackoverflow":"","wechat":"","qq":"","weibo":"","zhihu":"","csdn":"https://blog.csdn.net/m0_51898303","juejin":"","customs":{}}}}]}